nuclia_models-0.52.1.dist-info/METADATA
nuclia_models-0.52.1.dist-info/WHEEL
nuclia_models-0.52.1.dist-info/entry_points.txt
nuclia_models-0.52.1.dist-info/licenses/LICENSE.txt
nuclia_models-0.52.1.dist-info/licenses/LICENSE_Apache_v2.0.txt
nuclia_models/__init__.py
nuclia_models/accounts/__init__.py
nuclia_models/accounts/backups.py
nuclia_models/agent/__init__.py
nuclia_models/agent/api.py
nuclia_models/agent/interaction.py
nuclia_models/agent/memory.py
nuclia_models/common/__init__.py
nuclia_models/common/client.py
nuclia_models/common/consumption.py
nuclia_models/common/formats.py
nuclia_models/common/pagination.py
nuclia_models/common/user.py
nuclia_models/common/utils.py
nuclia_models/config/__init__.py
nuclia_models/config/proto.py
nuclia_models/events/__init__.py
nuclia_models/events/activity_logs.py
nuclia_models/events/remi.py
nuclia_models/predict/__init__.py
nuclia_models/predict/generative_responses.py
nuclia_models/predict/remi.py
nuclia_models/predict/run_agents.py
nuclia_models/py.typed
nuclia_models/worker/__init__.py
nuclia_models/worker/proto.py
nuclia_models/worker/tasks.py
nuclia_models/worker/triggers.py
nuclia_models-0.52.1.dist-info/RECORD
