Metadata-Version: 2.4
Name: nuclia-models
Version: 0.52.1
License-Expression: Apache-2.0
Requires-Python: >=3.9
Requires-Dist: pydantic[email]>=2.11
